sh_crypt/__init__.py
sh_crypt/crypt.py
sh_crypt/gen_key.py
sh_crypt-1.2.1.dist-info/LICENSE
sh_crypt-1.2.1.dist-info/METADATA
sh_crypt-1.2.1.dist-info/WHEEL
sh_crypt-1.2.1.dist-info/top_level.txt
sh_crypt-1.2.1.dist-info/RECORD
