Metadata-Version: 2.1
Name: sh-crypt
Version: 1.2.1
Summary: Simple symmetric encryption and decryption (ECB) for text
Author-email: Steven HELLEC <steven.hellc@live.fr>
License: MIT license
Project-URL: Source, https://github.com/steven1909/sh-crypt.git
Project-URL: PyPI, https://pypi.org/project/sh-crypt/
Keywords: encryption,decryption,cipher,AES,ECB,crypto,cryptography
Classifier: Intended Audience :: Developers
Classifier: Topic :: Security :: Cryptography
Classifier: Topic :: Security
Classifier: Development Status :: 5 - Production/Stable
Classifier: Natural Language :: English
Classifier: License :: OSI Approved :: MIT License
Classifier: Operating System :: POSIX :: Linux
Classifier: Programming Language :: Python :: 3
Requires-Python: >=3.7
License-File: LICENSE
Requires-Dist: cryptography (>=37.0.4)
